mindx/__init__.py
mindx/_exception_monitor.py
mindx/restore_manager.py
mindx-0.0.13.dist-info/METADATA
mindx-0.0.13.dist-info/WHEEL
mindx-0.0.13.dist-info/top_level.txt
mindx-0.0.13.dist-info/RECORD
