Metadata-Version: 2.1
Name: mindx
Version: 0.0.13
Summary: mindx
Home-page: https://gitee.com/ascend/ascend-deployer
License: Apache
Platform: UNKNOWN
Classifier: Programming Language :: Python :: 3
Classifier: License :: OSI Approved :: Apache Software License
Classifier: Operating System :: OS Independent
Requires-Python: >= 3.6
Requires-Dist: mindspore (>=1.0.0)
